decide/__init__.py
decide/auth.py
decide/globals.py
decide/models/__init__.py
decide/models/analysis.py
decide/models/base.py
decide/models/client.py
decide/models/customer.py
decide/models/enums.py
decide/models/error.py
decide/models/rules_engine.py
decide/models/statement.py
decide/models/tagged_statement.py
decide/test/__init__.py
decide/test/conftest.py
decide/test/helpers.py
decide/test/test_decide.py
decide/test/test_rules_engine.py
indicina_decide-0.5.1.dist-info/LICENSE.txt
indicina_decide-0.5.1.dist-info/METADATA
indicina_decide-0.5.1.dist-info/WHEEL
indicina_decide-0.5.1.dist-info/top_level.txt
indicina_decide-0.5.1.dist-info/RECORD
