Metadata-Version: 2.1
Name: indicina-decide
Version: 0.5.1
Author: Indicina Engineering
Classifier: Programming Language :: Python :: 3
License-File: LICENSE.txt
Requires-Dist: requests (==2.28.1)
Provides-Extra: dev
Requires-Dist: pre-commit (==2.20.0) ; extra == 'dev'
